README.md
setup.py
deka_dubbo/__init__.py
deka_dubbo/constant.py
deka_dubbo/dubbo_config.py
deka_dubbo/helpers.py
deka_dubbo/test01.py
deka_dubbo/test06.py
deka_dubbo/test7.py
deka_dubbo/test8.py
deka_dubbo.egg-info/PKG-INFO
deka_dubbo.egg-info/SOURCES.txt
deka_dubbo.egg-info/dependency_links.txt
deka_dubbo.egg-info/requires.txt
deka_dubbo.egg-info/top_level.txt
deka_dubbo/concurrent_pool/__init__.py
deka_dubbo/concurrent_pool/async_helper.py
deka_dubbo/concurrent_pool/async_pool_executor.py
deka_dubbo/concurrent_pool/custom_threadpool_executor.py
deka_dubbo/concurrent_pool/single_thread_executor.py
deka_dubbo/consumers/__init__.py
deka_dubbo/consumers/base_consumer.py
deka_dubbo/consumers/rabbitmq_amqpstorm_consumer.py
deka_dubbo/consumers/redis_filter.py
deka_dubbo/factories/__init__.py
deka_dubbo/factories/consumer_factory.py
deka_dubbo/factories/publisher_factory.py
deka_dubbo/publishers/__init__.py
deka_dubbo/publishers/base_publisher.py
deka_dubbo/publishers/rabbitmq_amqpstorm_publisher.py
deka_dubbo/utils/__init__.py
deka_dubbo/utils/decorators.py
deka_dubbo/utils/get_host_ip.py
deka_dubbo/utils/get_logger.py
deka_dubbo/utils/redis_manager.py
deka_dubbo/utils/simple_data_class.py
deka_dubbo/utils/time_util.py
deka_dubbo/utils/un_strict_json_dumps.py