Metadata-Version: 2.1
Name: deka-dubbo
Version: 1.0.2
Summary: rabbitmq为中间件的分布式任务框架
Author: zy
Author-email: 517826265@qq.com
Platform: all
